Metadata-Version: 2.1
Name: json2obj
Version: 1.0.2
Summary: Convert your JSON data to a valid Python object to allow accessing keys with the member access operator(.)
Home-page: https://github.com/trumpowen/json2obj
Author: Owen Trump
Author-email: trumpowen0@gmail.com
License: MIT
Platform: UNKNOWN
Classifier: License :: OSI Approved :: MIT License
Classifier: Programming Language :: Python :: 3
Requires-Python: >=3.6
